tess_stars2px.py
tess_point-0.9.3.dist-info/licenses/LICENSE
tess_point-0.9.3.dist-info/METADATA
tess_point-0.9.3.dist-info/WHEEL
tess_point-0.9.3.dist-info/top_level.txt
tess_point-0.9.3.dist-info/RECORD
