Metadata-Version: 2.4
Name: tess-point
Version: 0.9.3
Summary: Determine pixel coordinates for TESS targets
Home-page: https://github.com/christopherburke/tess-point
Author: Christopher J. Burke
Author-email: tesshelp@bigbang.gsfc.nasa.gov
License: MIT
Classifier: Programming Language :: Python :: 3
Classifier: License :: OSI Approved :: MIT License
Classifier: Operating System :: OS Independent
Classifier: Intended Audience :: Science/Research
Classifier: Topic :: Scientific/Engineering :: Astronomy
License-File: LICENSE
Requires-Dist: numpy
Requires-Dist: astropy
Requires-Dist: scipy
Dynamic: author
Dynamic: author-email
Dynamic: classifier
Dynamic: description
Dynamic: description-content-type
Dynamic: home-page
Dynamic: license
Dynamic: license-file
Dynamic: requires-dist
Dynamic: summary
